odoo/addons/mrp_bom_component_menu/README.rst
odoo/addons/mrp_bom_component_menu/__init__.py
odoo/addons/mrp_bom_component_menu/__manifest__.py
odoo/addons/mrp_bom_component_menu/i18n/de.po
odoo/addons/mrp_bom_component_menu/i18n/fr.po
odoo/addons/mrp_bom_component_menu/i18n/fr_FR.po
odoo/addons/mrp_bom_component_menu/i18n/it.po
odoo/addons/mrp_bom_component_menu/i18n/mrp_bom_component_menu.pot
odoo/addons/mrp_bom_component_menu/i18n/pt_BR.po
odoo/addons/mrp_bom_component_menu/i18n/zh_CN.po
odoo/addons/mrp_bom_component_menu/static/description/icon.png
odoo/addons/mrp_bom_component_menu/views/mrp_bom_component_view.xml
odoo12_addon_mrp_bom_component_menu-12.0.1.0.0.99.dev16.dist-info/METADATA
odoo12_addon_mrp_bom_component_menu-12.0.1.0.0.99.dev16.dist-info/WHEEL
odoo12_addon_mrp_bom_component_menu-12.0.1.0.0.99.dev16.dist-info/top_level.txt
odoo12_addon_mrp_bom_component_menu-12.0.1.0.0.99.dev16.dist-info/RECORD
